clipthegym
