Metadata-Version: 1.1
Name: clip-the-gym
Version: 0.0.2
Summary: Helper script to download audio from youtube for the gym
Home-page: http://github.com/ralphbean/clip-the-gym
Author: Ralph Bean
Author-email: rbean@redhat.com
License: GPLv3+
Platform: UNKNOWN
Classifier: Development Status :: 4 - Beta
Classifier: Intended Audience :: Developers
Classifier: Intended Audience :: End Users/Desktop
Classifier: License :: OSI Approved :: GNU General Public License (GPL)
Classifier: Programming Language :: Python
Classifier: Programming Language :: Python :: 2.5
Classifier: Programming Language :: Python :: 2.6
Classifier: Programming Language :: Python :: 2.7
Classifier: Topic :: Internet :: WWW/HTTP
Classifier: Topic :: Text Processing :: General
